smipc/__init__.py
smipc/arguments.py
smipc/entrypoint.py
smipc/variables.py
smipc/aio/__init__.py
smipc/aio/run.py
smipc/apps/__init__.py
smipc/apps/client.py
smipc/apps/server.py
smipc/cuda/__init__.py
smipc/cuda/alignment.py
smipc/cuda/compatibility.py
smipc/cuda/dtype.py
smipc/cuda/runtime.py
smipc/cuda/ipc/__init__.py
smipc/cuda/ipc/packet.py
smipc/cuda/ipc/provider.py
smipc/cuda/ipc/receiver.py
smipc/decorators/__init__.py
smipc/decorators/override.py
smipc/pipe/__init__.py
smipc/pipe/conf.py
smipc/pipe/duplex.py
smipc/pipe/file.py
smipc/pipe/flags.py
smipc/pipe/reader.py
smipc/pipe/temp.py
smipc/pipe/temp_pair.py
smipc/pipe/wait.py
smipc/pipe/writer.py
smipc/protocols/__init__.py
smipc/protocols/base.py
smipc/protocols/header.py
smipc/protocols/sm.py
smipc/pubsub/__init__.py
smipc/pubsub/publisher.py
smipc/pubsub/subscriber.py
smipc/server/__init__.py
smipc/server/base.py
smipc/server/aio/__init__.py
smipc/server/aio/base.py
smipc/server/aio/echo.py
smipc/server/aio/queue.py
smipc/sm/__init__.py
smipc/sm/queue.py
smipc/sm/utils.py
smipc/sm/validator.py
smipc/sm/written.py
smipc-0.1.1.dist-info/LICENSE
smipc-0.1.1.dist-info/METADATA
smipc-0.1.1.dist-info/WHEEL
smipc-0.1.1.dist-info/top_level.txt
smipc-0.1.1.dist-info/RECORD
