Metadata-Version: 2.1
Name: smipc
Version: 0.1.1
Summary: Shared Memory IPC
Home-page: https://github.com/osom8979/smipc
Author: zer0
Author-email: osom8979@gmail.com
License: MIT License
Project-URL: GitHub: issues, https://github.com/osom8979/smipc/issues
Project-URL: GitHub: repo, https://github.com/osom8979/smipc
Platform: UNKNOWN
Classifier: Development Status :: 4 - Beta
Classifier: Intended Audience :: Developers
Classifier: Operating System :: OS Independent
Classifier: Programming Language :: Python
Classifier: Programming Language :: Python :: 3.9
Classifier: Topic :: Software Development
Classifier: Topic :: Utilities
Classifier: License :: OSI Approved :: MIT License
Requires-Python: >=3.9
License-File: LICENSE
Requires-Dist: numpy
